pypypan/__init__.py
pypypan/excel.py
pypypan/main.py
pypypan/upload.py
pypypan-0.8.0.dist-info/entry_points.txt
pypypan-0.8.0.dist-info/WHEEL
pypypan-0.8.0.dist-info/METADATA
pypypan-0.8.0.dist-info/RECORD
