Metadata-Version: 2.1
Name: pypypan
Version: 0.8.0
Summary: 
Author: Ate te Voortwis
Author-email: atv@allseas.com
Requires-Python: >=3.8,<4.0
Classifier: Programming Language :: Python :: 3
Classifier: Programming Language :: Python :: 3.10
Classifier: Programming Language :: Python :: 3.8
Classifier: Programming Language :: Python :: 3.9
Requires-Dist: pandas (>=1.4.0,<2.0.0)
Requires-Dist: pywikibot (>=6.6.3,<7.0.0)
Requires-Dist: requests-oauthlib (>=1.3.0,<2.0.0)
Requires-Dist: typer (>=0.4.0,<0.5.0)
Requires-Dist: wikitextparser (>=0.48.0,<0.49.0)
Requires-Dist: xlrd (>=2.0.1,<3.0.0)
